esphome_dashboard/__init__.py
esphome_dashboard/base.template.html
esphome_dashboard/base_with_header_footer.template.html
esphome_dashboard/index.template.html
esphome_dashboard/login.template.html
esphome_dashboard/static/css/esphome-2.css
esphome_dashboard/static/firmware/bootloader.bin
esphome_dashboard/static/firmware/ota.bin
esphome_dashboard/static/firmware/partitions.bin
esphome_dashboard/static/fonts/codicon.ttf
esphome_dashboard/static/fonts/material-icons/LICENSE
esphome_dashboard/static/fonts/material-icons/MaterialIcons-Regular.woff
esphome_dashboard/static/fonts/material-icons/MaterialIcons-Regular.woff2
esphome_dashboard/static/fonts/material-icons/README.md
esphome_dashboard/static/fonts/material-icons/material-icons.css
esphome_dashboard/static/images/favicon.ico
esphome_dashboard/static/images/logo-text.svg
esphome_dashboard/static/js/esphome/c.005c09ab.js
esphome_dashboard/static/js/esphome/c.0117db04.js
esphome_dashboard/static/js/esphome/c.09c62faa.js
esphome_dashboard/static/js/esphome/c.09d680a6.js
esphome_dashboard/static/js/esphome/c.0aaa76c4.js
esphome_dashboard/static/js/esphome/c.0b5f627c.js
esphome_dashboard/static/js/esphome/c.0d66249f.js
esphome_dashboard/static/js/esphome/c.13f7e761.js
esphome_dashboard/static/js/esphome/c.1f63e768.js
esphome_dashboard/static/js/esphome/c.286ad693.js
esphome_dashboard/static/js/esphome/c.2cde0e0b.js
esphome_dashboard/static/js/esphome/c.30a0677d.js
esphome_dashboard/static/js/esphome/c.32c39114.js
esphome_dashboard/static/js/esphome/c.33591792.js
esphome_dashboard/static/js/esphome/c.3efd377c.js
esphome_dashboard/static/js/esphome/c.417d3d2d.js
esphome_dashboard/static/js/esphome/c.419250e6.js
esphome_dashboard/static/js/esphome/c.440fff61.js
esphome_dashboard/static/js/esphome/c.5cd5d307.js
esphome_dashboard/static/js/esphome/c.5d2523d4.js
esphome_dashboard/static/js/esphome/c.63fcbfd6.js
esphome_dashboard/static/js/esphome/c.6ed02c37.js
esphome_dashboard/static/js/esphome/c.720b19aa.js
libretiny_esphome_dashboard-20230214.0.dist-info/LICENSE
libretiny_esphome_dashboard-20230214.0.dist-info/METADATA
libretiny_esphome_dashboard-20230214.0.dist-info/WHEEL
libretiny_esphome_dashboard-20230214.0.dist-info/top_level.txt
libretiny_esphome_dashboard-20230214.0.dist-info/RECORD
