Metadata-Version: 2.1
Name: libretiny-esphome-dashboard
Version: 20230214.0
Summary: ESPHome dashboard
Home-page: https://github.com/esphome/dashboard
Author: Nabu Casa
Author-email: hello@nabucasa.com
License: Apache-2.0
License-File: LICENSE
